nlohmann_json/__init__.py
nlohmann_json/include/__init__.py
nlohmann_json/include/nlohmann/adl_serializer.hpp
nlohmann_json/include/nlohmann/byte_container_with_subtype.hpp
nlohmann_json/include/nlohmann/json.hpp
nlohmann_json/include/nlohmann/json_fwd.hpp
nlohmann_json/include/nlohmann/ordered_map.hpp
nlohmann_json/include/nlohmann/detail/abi_macros.hpp
nlohmann_json/include/nlohmann/detail/exceptions.hpp
nlohmann_json/include/nlohmann/detail/hash.hpp
nlohmann_json/include/nlohmann/detail/json_pointer.hpp
nlohmann_json/include/nlohmann/detail/json_ref.hpp
nlohmann_json/include/nlohmann/detail/macro_scope.hpp
nlohmann_json/include/nlohmann/detail/macro_unscope.hpp
nlohmann_json/include/nlohmann/detail/string_concat.hpp
nlohmann_json/include/nlohmann/detail/string_escape.hpp
nlohmann_json/include/nlohmann/detail/value_t.hpp
nlohmann_json/include/nlohmann/detail/conversions/from_json.hpp
nlohmann_json/include/nlohmann/detail/conversions/to_chars.hpp
nlohmann_json/include/nlohmann/detail/conversions/to_json.hpp
nlohmann_json/include/nlohmann/detail/input/binary_reader.hpp
nlohmann_json/include/nlohmann/detail/input/input_adapters.hpp
nlohmann_json/include/nlohmann/detail/input/json_sax.hpp
nlohmann_json/include/nlohmann/detail/input/lexer.hpp
nlohmann_json/include/nlohmann/detail/input/parser.hpp
nlohmann_json/include/nlohmann/detail/input/position_t.hpp
nlohmann_json/include/nlohmann/detail/iterators/internal_iterator.hpp
nlohmann_json/include/nlohmann/detail/iterators/iter_impl.hpp
nlohmann_json/include/nlohmann/detail/iterators/iteration_proxy.hpp
nlohmann_json/include/nlohmann/detail/iterators/iterator_traits.hpp
nlohmann_json/include/nlohmann/detail/iterators/json_reverse_iterator.hpp
nlohmann_json/include/nlohmann/detail/iterators/primitive_iterator.hpp
nlohmann_json/include/nlohmann/detail/meta/cpp_future.hpp
nlohmann_json/include/nlohmann/detail/meta/detected.hpp
nlohmann_json/include/nlohmann/detail/meta/identity_tag.hpp
nlohmann_json-3.11.2.dist-info/LICENSE
nlohmann_json-3.11.2.dist-info/METADATA
nlohmann_json-3.11.2.dist-info/WHEEL
nlohmann_json-3.11.2.dist-info/top_level.txt
nlohmann_json-3.11.2.dist-info/RECORD
