Metadata-Version: 2.1
Name: nlohmann-json
Version: 3.11.2
Summary: Repackaging of nlohmann-json distributed via PyPI
Author-email: Alliander Dynamic Grid Calculation <dynamic.grid.calculation@alliander.com>
License: MIT
Project-URL: Home-page, http://github.com/nlohmann/json
Project-URL: GitHub, http://github.com/nlohmann/json
Project-URL: Documentation, http://nlohmann.github.io/json/
Classifier: Programming Language :: C++
Classifier: Development Status :: 5 - Production/Stable
Classifier: Intended Audience :: Developers
Classifier: License :: OSI Approved :: MIT License
Classifier: Operating System :: Microsoft :: Windows
Classifier: Operating System :: POSIX :: Linux
Classifier: Operating System :: MacOS
Classifier: Topic :: File Formats
Classifier: Topic :: Software Development :: Libraries
License-File: LICENSE
Requires-Dist: importlib-resources
Provides-Extra: dev
Requires-Dist: pytest ; extra == 'dev'
